{"id":12121,"author":null,"author_avatar_url":null,"author_id":572,"author_status":1,"gmt_create":1645776161474,"gmt_modified":1645776161474,"content":"请问管理数学考试能带计算器吗","title":"请问管理数学考试能带计算器吗","description":"no description yet","like_count":0,"comment_count":2,"view_count":84,"type":"post","tag":"not tag yet","imageList":"","content_source":null,"comments":[{"id":44736,"parent_id":12121,"type":1,"commentor":579,"gmtCreate":null,"gmtModified":null,"like_count":0,"content":"不能","anonymity":1,"any_name":"老板","commentCount":null,"user":{"id":579,"name":"tina","avatar_url":"http://test01-20200725.oss-cn-shenzhen.aliyuncs.com/image/1663074679074.jpg?Expires=1978434670&OSSAccessKeyId=LTAI4G5RL7pjavqASCwc42kR&Signature=szFYPjMagOfEExY1s9roPQwJrEA%3D"},"isCommentLike":-5,"dislike_count":0},{"id":44737,"parent_id":12121,"type":1,"commentor":772,"gmtCreate":null,"gmtModified":null,"like_count":0,"content":"nono","anonymity":1,"any_name":"芋圆奶茶","commentCount":null,"user":{"id":772,"name":"人鱼岛","avatar_url":"http://test01-20200725.oss-cn-shenzhen.aliyuncs.com/image/1655263848705.jpg?Expires=1970623841&OSSAccessKeyId=LTAI4G5RL7pjavqASCwc42kR&Signature=4LGv6mJQXC2XZHHRZzUDAlYKc1U%3D"},"isCommentLike":-5,"dislike_count":0}],"any_name":"大潭山车队","relation":-2,"liked":-4,"anonymity":1,"dislike_count":0}