{"id":14091,"author":null,"author_avatar_url":null,"author_id":830,"author_status":1,"gmt_create":1647452421758,"gmt_modified":1647452421758,"content":"好纠结……到底要不要入ooo的腰带啊……","title":"好纠结……到底要不要入ooo的腰带啊……","description":"no description yet","like_count":0,"comment_count":2,"view_count":121,"type":"post","tag":"not tag yet","imageList":"","content_source":null,"comments":[{"id":52361,"parent_id":14091,"type":1,"commentor":1030,"gmtCreate":null,"gmtModified":null,"like_count":0,"content":"建议入，因为还得涨，已经后悔之前没买csm了，而且ooo的人气一直很高，像我这种ooo入圈的绝对会买。","anonymity":1,"any_name":"皮卡丘","commentCount":null,"user":{"id":1030,"name":"123","avatar_url":"https://thirdwx.qlogo.cn/mmopen/vi_32/Smk8O2z6R0icvg8tkqibbVKraxvIu5n9iaHeD0RHJUQm7ygiaOiauUsyETK96ZdS9rDIiaozYUo8rMa1EcM8fBdHibj4w/132"},"isCommentLike":-5,"dislike_count":0},{"id":52364,"parent_id":14091,"type":1,"commentor":351,"gmtCreate":null,"gmtModified":null,"like_count":0,"content":"冲就完了，ooo腰带针滴帅","anonymity":1,"any_name":"拱北快递员","commentCount":null,"user":{"id":351,"name":"dvdvdv","avatar_url":"http://test01-20200725.oss-cn-shenzhen.aliyuncs.com/image/1651334456439.jpg?Expires=1966694454&OSSAccessKeyId=LTAI4G5RL7pjavqASCwc42kR&Signature=CR5vv9gO7mSFgrOXK0Xk3x7eEBw%3D"},"isCommentLike":-5,"dislike_count":0}],"any_name":"四川麻辣烫","relation":-2,"liked":-4,"anonymity":1,"dislike_count":0}