{"id":14798,"author":"arT","author_avatar_url":"https://thirdwx.qlogo.cn/mmopen/vi_32/lyFAqR0AcYYRMtzHlicqCOliapHIFJ4ye0zpH6lGPKgGAzeomuxGgDNWKicJE7fh5p2qjNUzQSRj0eWKmTu1W2lOg/132","author_id":2104,"author_status":1,"gmt_create":1647954551206,"gmt_modified":1647954551206,"content":"lol艾欧尼亚 KiloKale大乱斗一起玩：）","title":"lol艾欧尼亚 KiloKale大乱斗一起玩：）","description":"no description yet","like_count":1,"comment_count":1,"view_count":30,"type":"post","tag":"not tag yet","imageList":"","content_source":null,"comments":[{"id":55637,"parent_id":14798,"type":1,"commentor":4881,"gmtCreate":null,"gmtModified":null,"like_count":0,"content":"留个好友以后开黑","anonymity":0,"any_name":null,"commentCount":null,"user":{"id":4881,"name":"卷积神经网络","avatar_url":null},"isCommentLike":-5,"dislike_count":0}],"any_name":null,"relation":-2,"liked":-4,"anonymity":0,"dislike_count":0}