{"id":19041,"author":null,"author_avatar_url":null,"author_id":635,"author_status":1,"gmt_create":1650685900947,"gmt_modified":1650685900947,"content":"我是谁？","title":"我是谁？","description":"no description yet","like_count":1,"comment_count":2,"view_count":69,"type":"post","tag":"not tag yet","imageList":"","content_source":null,"comments":[{"id":71703,"parent_id":19041,"type":1,"commentor":1655,"gmtCreate":null,"gmtModified":null,"like_count":0,"content":"妙蛙种子！","anonymity":1,"any_name":"六级词汇","commentCount":null,"user":{"id":1655,"name":"应急食品（毕业版）","avatar_url":"http://test01-20200725.oss-cn-shenzhen.aliyuncs.com/image/1636378464049.gif?Expires=1951738454&OSSAccessKeyId=LTAI4G5RL7pjavqASCwc42kR&Signature=Ay0yzvZwaOrfFrXfYrxsTdpLkwM%3D"},"isCommentLike":-5,"dislike_count":0},{"id":71730,"parent_id":19041,"type":1,"commentor":682,"gmtCreate":null,"gmtModified":null,"like_count":0,"content":"你是一个，一个一个一个，啊，啊啊啊啊啊啊","anonymity":0,"any_name":null,"commentCount":null,"user":{"id":682,"name":"~Xenon~","avatar_url":"http://test01-20200725.oss-cn-shenzhen.aliyuncs.com/image/1662451495431.gif?Expires=1977811496&OSSAccessKeyId=LTAI4G5RL7pjavqASCwc42kR&Signature=tLEL737zMefpEHXZzQlS%2Bxz88Ts%3D"},"isCommentLike":-5,"dislike_count":0}],"any_name":"Anton","relation":-2,"liked":-4,"anonymity":1,"dislike_count":0}