{"id":20001,"author":"科大鸭","author_avatar_url":"http://test01-20200725.oss-cn-shenzhen.aliyuncs.com/image/1624370407433.jpeg?Expires=1939730402&OSSAccessKeyId=LTAI4G5RL7pjavqASCwc42kR&Signature=UEIvjfVREj9DPr4FHeyAIel3Guo%3D","author_id":15,"author_status":6,"gmt_create":1651236148935,"gmt_modified":1651236148935,"content":"刚刚树洞出现问题，现已恢复。\n大家可以正常使用了！\n感谢大家对树洞一直以来的理解与支持！","title":"刚刚树洞出现问题，现已恢复。\n大家可以正常使用了！\n感谢大家对树洞一直以来的理解与支持！","description":"no description yet","like_count":7,"comment_count":1,"view_count":83,"type":"post","tag":"not tag yet","imageList":"","content_source":null,"comments":[{"id":75489,"parent_id":20001,"type":1,"commentor":1295,"gmtCreate":null,"gmtModified":null,"like_count":0,"content":"鸭鸭辛苦啦！","anonymity":1,"any_name":"奥利奥","commentCount":null,"user":{"id":1295,"name":"U_637031633831","avatar_url":null},"isCommentLike":-5,"dislike_count":0}],"any_name":null,"relation":-2,"liked":-4,"anonymity":0,"dislike_count":0}