{"id":21452,"author":null,"author_avatar_url":null,"author_id":1475,"author_status":1,"gmt_create":1652106616115,"gmt_modified":1652106616115,"content":"coes 我***你妈了个*的有钱发卫星没钱修修你那b服务器\n我都开始confirm了，你能跟我开出来我真是吐了","title":"coes 我***你妈了个*的有钱发卫星没钱修修你那b服务器\n我都开始confirm了，你能跟我开出来我真是吐了","description":"no description yet","like_count":6,"comment_count":2,"view_count":289,"type":"post","tag":"not tag yet","imageList":"","content_source":null,"comments":[{"id":80359,"parent_id":21452,"type":1,"commentor":504,"gmtCreate":null,"gmtModified":null,"like_count":3,"content":"麻辣烫好骂","anonymity":0,"any_name":null,"commentCount":null,"user":{"id":504,"name":"maito","avatar_url":"https://thirdwx.qlogo.cn/mmopen/vi_32/ILBrJqNk3JEwZswoaDQ5RghfFWOf6PToUEUze5shr1icVFI7oT6TbcGUZuibdpictDibwicVUkKDiaT4FFgmwNN43yPQ/132"},"isCommentLike":-5,"dislike_count":0},{"id":80357,"parent_id":21452,"type":1,"commentor":881,"gmtCreate":null,"gmtModified":null,"like_count":0,"content":"后退就行了 不用刷新 刷新就出去了","anonymity":1,"any_name":"出前一丁","commentCount":null,"user":{"id":881,"name":"明天一定会早起","avatar_url":"http://test01-20200725.oss-cn-shenzhen.aliyuncs.com/image/1647250276351.jpg?Expires=1962610271&OSSAccessKeyId=LTAI4G5RL7pjavqASCwc42kR&Signature=GVEEMU%2BBoifUCu3nR%2FFAnmKAHc8%3D"},"isCommentLike":-5,"dislike_count":0}],"any_name":"四川麻辣烫","relation":-2,"liked":-4,"anonymity":1,"dislike_count":0}