{"id":25478,"author":null,"author_avatar_url":null,"author_id":9117,"author_status":1,"gmt_create":1653581521291,"gmt_modified":1653581521291,"content":"第一天上班，简直是消息轰炸","title":"第一天上班，简直是消息轰炸","description":"no description yet","like_count":0,"comment_count":3,"view_count":184,"type":"post","tag":"not tag yet","imageList":"","content_source":null,"comments":[{"id":93057,"parent_id":25478,"type":1,"commentor":9117,"gmtCreate":null,"gmtModified":null,"like_count":0,"content":"累啊","anonymity":1,"any_name":"拱北快递员","commentCount":null,"user":{"id":9117,"name":"U_66691653581","avatar_url":null},"isCommentLike":-5,"dislike_count":0},{"id":93064,"parent_id":25478,"type":1,"commentor":1194,"gmtCreate":null,"gmtModified":null,"like_count":0,"content":"上班是什么感觉\uD83D\uDE2D","anonymity":1,"any_name":"喷火龙","commentCount":null,"user":{"id":1194,"name":"神经蛙","avatar_url":"https://thirdwx.qlogo.cn/mmopen/vi_32/Q3auHgzwzM7pNkMMHY91xibhlhm06YjFvq6xpoNMEgFNfjyB2yHsl7afwibtLn8OYGOxMiciap8bK6mC67FxAwcPxA/132"},"isCommentLike":-5,"dislike_count":0},{"id":93065,"parent_id":93064,"type":2,"commentor":9117,"gmtCreate":null,"gmtModified":null,"like_count":0,"content":"紧张又焦虑","anonymity":1,"any_name":"拱北快递员","commentCount":null,"user":{"id":9117,"name":"U_66691653581","avatar_url":null},"isCommentLike":-5,"dislike_count":0}],"any_name":"拱北快递员","relation":-2,"liked":-4,"anonymity":1,"dislike_count":0}