{"id":27492,"author":"~Xenon~","author_avatar_url":"http://test01-20200725.oss-cn-shenzhen.aliyuncs.com/image/1662451495431.gif?Expires=1977811496&OSSAccessKeyId=LTAI4G5RL7pjavqASCwc42kR&Signature=tLEL737zMefpEHXZzQlS%2Bxz88Ts%3D","author_id":682,"author_status":1,"gmt_create":1655305676287,"gmt_modified":1655305676287,"content":"怎么广州铁博外场的机车和车底被淹成这样了555\n雨能不能停一停，我还想去参观一下呢","title":"怎么广州铁博外场的机车和车底被淹成这样了555\n雨能不能停一停，我还想去参观一下呢","description":"no description yet","like_count":0,"comment_count":0,"view_count":16,"type":"post","tag":"not tag yet","imageList":"http://test01-20200725.oss-cn-shenzhen.aliyuncs.com/image/1655305672618.jpg?Expires=1970665673&OSSAccessKeyId=LTAI4G5RL7pjavqASCwc42kR&Signature=1ZjIwwOtp6FBfBcZuAGqM1Yihj4%3D","content_source":null,"comments":null,"any_name":null,"relation":-2,"liked":-4,"anonymity":0,"dislike_count":0}