{"id":31425,"author":"美女","author_avatar_url":"http://test01-20200725.oss-cn-shenzhen.aliyuncs.com/image/1666772348398.jpg?Expires=1982132345&OSSAccessKeyId=LTAI4G5RL7pjavqASCwc42kR&Signature=IEgc9LHzgpsotqCWqRd05bXUxtE%3D","author_id":106,"author_status":1,"gmt_create":1658408263249,"gmt_modified":1658408263249,"content":"请问横琴朗莘雅思怎么样","title":"请问横琴朗莘雅思怎么样","description":"no description yet","like_count":2,"comment_count":1,"view_count":117,"type":"post","tag":"not tag yet","imageList":"","content_source":null,"comments":[{"id":119894,"parent_id":31425,"type":1,"commentor":8840,"gmtCreate":null,"gmtModified":null,"like_count":0,"content":"上过 不咋地","anonymity":1,"any_name":"亚古兽","commentCount":null,"user":{"id":8840,"name":"夹心饼干","avatar_url":null},"isCommentLike":-5,"dislike_count":0}],"any_name":null,"relation":-2,"liked":-4,"anonymity":0,"dislike_count":0}