{"id":38660,"author":null,"author_avatar_url":null,"author_id":9724,"author_status":1,"gmt_create":1663436402426,"gmt_modified":1663436402426,"content":"暑假碰到个人都是家里派来叫我读研的，回来上一周课，只想开摆\uD83D\uDE11 宿舍越住越憋屈，每科个顶个的k，该摆了","title":"暑假碰到个人都是家里派来叫我读研的，回来上一周课，只想开摆\uD83D\uDE11 宿舍越住越憋屈，每科个顶个的k，该摆了","description":"no description yet","like_count":1,"comment_count":2,"view_count":251,"type":"post","tag":"not tag yet","imageList":"","content_source":null,"comments":[{"id":147927,"parent_id":38660,"type":1,"commentor":9724,"gmtCreate":null,"gmtModified":null,"like_count":0,"content":"读小语种比较好的就是，反正本科学历没人要，不如选个便宜点的\uD83D\uDE0B","anonymity":1,"any_name":"Redis设计与实现","commentCount":null,"user":{"id":9724,"name":"睡觉第一","avatar_url":"http://test01-20200725.oss-cn-shenzhen.aliyuncs.com/image/1661957207803.jpg?Expires=1977317203&OSSAccessKeyId=LTAI4G5RL7pjavqASCwc42kR&Signature=Z3Etx1GjD5n%2FrA71eWyIhWAhLks%3D"},"isCommentLike":-5,"dislike_count":0},{"id":147969,"parent_id":38660,"type":1,"commentor":530,"gmtCreate":null,"gmtModified":null,"like_count":0,"content":"什么专业哇","anonymity":1,"any_name":"微积分","commentCount":null,"user":{"id":530,"name":"黄昏里","avatar_url":"http://test01-20200725.oss-cn-shenzhen.aliyuncs.com/image/1631114816080.jpg?Expires=1946474809&OSSAccessKeyId=LTAI4G5RL7pjavqASCwc42kR&Signature=GUAT5Hw5mYtyrb6W2s2hajNWJZk%3D"},"isCommentLike":-5,"dislike_count":0}],"any_name":"Redis设计与实现","relation":-2,"liked":-4,"anonymity":1,"dislike_count":0}