{"id":40167,"author":null,"author_avatar_url":null,"author_id":1380,"author_status":1,"gmt_create":1664182859650,"gmt_modified":1664182859650,"content":"不在共同笑点上的分享欲真的很尴尬，不熟的人没有任何共同话题只是丢视频过来，问是不是艾特错人了，然后就把我删了，挺搞笑的，在朋友圈发过希望大家能认同他骂前女友的话，虽然他前女友是渣女，经常看见的动态都是想恋爱的，真的不喜欢带着目的性接近的人，本以为你会是有趣的人","title":"不在共同笑点上的分享欲真的很尴尬，不熟的人没有任何共同话题只是丢视频过来，问是不是艾特错人了，然后就把我删了，挺搞笑的，在朋友圈发过希望大家能认同他骂前女友的话，虽然他前","description":"no description yet","like_count":0,"comment_count":1,"view_count":116,"type":"post","tag":"not tag yet","imageList":"","content_source":null,"comments":[{"id":153493,"parent_id":40167,"type":1,"commentor":1202,"gmtCreate":null,"gmtModified":null,"like_count":0,"content":"分了手还嘴对方，不管是男女，都挺下头的","anonymity":1,"any_name":"老板","commentCount":null,"user":{"id":1202,"name":"啵啵唧唧\uD83D\uDC99","avatar_url":"https://thirdwx.qlogo.cn/mmopen/vi_32/I70894NAGzAicERAmfibaZjDyIKgat5by7F5pfWBAeqSPI53NBliaoGBwtz1VoNu0h6XGWeiaOlibib9oEDaCgbE6OxA/132"},"isCommentLike":-5,"dislike_count":0}],"any_name":"英国短毛猫","relation":-2,"liked":-4,"anonymity":1,"dislike_count":0}