{"id":42069,"author":null,"author_avatar_url":null,"author_id":9882,"author_status":1,"gmt_create":1665061432325,"gmt_modified":1665061432325,"content":"明晚6:40有没有霉粉想去星皓广场看电影领明信片的\uD83E\uDD79在线等","title":"明晚6:40有没有霉粉想去星皓广场看电影领明信片的\uD83E\uDD79在线等","description":"no description yet","like_count":0,"comment_count":7,"view_count":180,"type":"post","tag":"not tag yet","imageList":"","content_source":null,"comments":[{"id":160440,"parent_id":42069,"type":1,"commentor":9078,"gmtCreate":null,"gmtModified":null,"like_count":0,"content":"怎么买票","anonymity":1,"any_name":"和味牛杂","commentCount":null,"user":{"id":9078,"name":"U_461661653494","avatar_url":null},"isCommentLike":-5,"dislike_count":0},{"id":160493,"parent_id":42069,"type":1,"commentor":1241,"gmtCreate":null,"gmtModified":null,"like_count":0,"content":"可以代领明信片吗\uD83E\uDD7A","anonymity":1,"any_name":"Anton","commentCount":null,"user":{"id":1241,"name":"lilies","avatar_url":"http://test01-20200725.oss-cn-shenzhen.aliyuncs.com/image/1638097225372.jpg?Expires=1953457215&OSSAccessKeyId=LTAI4G5RL7pjavqASCwc42kR&Signature=ZpjZjuO%2F13e8TqPdcS8PmwI1kjE%3D"},"isCommentLike":-5,"dislike_count":0},{"id":160504,"parent_id":42069,"type":1,"commentor":9473,"gmtCreate":null,"gmtModified":null,"like_count":0,"content":"可以不买票直接去现场领，我朋友刚刚去领到了","anonymity":1,"any_name":"鸡蛋仔","commentCount":null,"user":{"id":9473,"name":"开麦","avatar_url":"http://test01-20200725.oss-cn-shenzhen.aliyuncs.com/image/1659093269220.jpg?Expires=1974453266&OSSAccessKeyId=LTAI4G5RL7pjavqASCwc42kR&Signature=iXP02t%2FQTcfthAK18FxqIRxdBIY%3D"},"isCommentLike":-5,"dislike_count":0},{"id":160674,"parent_id":42069,"type":1,"commentor":8416,"gmtCreate":null,"gmtModified":null,"like_count":0,"content":"明信片是什么东西？是有什么活动吗？","anonymity":1,"any_name":"珠海小天使","commentCount":null,"user":{"id":8416,"name":"U_479271652854","avatar_url":null},"isCommentLike":-5,"dislike_count":0},{"id":160443,"parent_id":160440,"type":2,"commentor":9882,"gmtCreate":null,"gmtModified":null,"like_count":0,"content":"网上信用卡订票or现场买票","anonymity":0,"any_name":null,"commentCount":null,"user":{"id":9882,"name":"老公孩子在天堂","avatar_url":null},"isCommentLike":-5,"dislike_count":0},{"id":160675,"parent_id":160674,"type":2,"commentor":8416,"gmtCreate":null,"gmtModified":null,"like_count":0,"content":"我是说，是什么类型的明信片?","anonymity":1,"any_name":"水箭龟","commentCount":null,"user":{"id":8416,"name":"U_479271652854","avatar_url":null},"isCommentLike":-5,"dislike_count":0},{"id":160758,"parent_id":160504,"type":2,"commentor":9078,"gmtCreate":null,"gmtModified":null,"like_count":0,"content":"可以问问你在哪个电影院吗","anonymity":1,"any_name":"和味牛杂","commentCount":null,"user":{"id":9078,"name":"U_461661653494","avatar_url":null},"isCommentLike":-5,"dislike_count":0}],"any_name":"GRE精选","relation":-2,"liked":-4,"anonymity":1,"dislike_count":0}