{"id":43818,"author":null,"author_avatar_url":null,"author_id":907,"author_status":1,"gmt_create":1665774780958,"gmt_modified":1665774780958,"content":"有没有上过行政学的同学/学长学姐啊\n课堂参与要占分吗？？、\n有没有拿过A的论文能参考下\uD83D\uDE2D","title":"有没有上过行政学的同学/学长学姐啊\n课堂参与要占分吗？？、\n有没有拿过A的论文能参考下\uD83D\uDE2D","description":"no description yet","like_count":1,"comment_count":0,"view_count":13,"type":"post","tag":"not tag yet","imageList":"","content_source":null,"comments":null,"any_name":"Jerry","relation":-2,"liked":-4,"anonymity":1,"dislike_count":0}