{"id":45191,"author":null,"author_avatar_url":null,"author_id":1025,"author_status":1,"gmt_create":1666235504333,"gmt_modified":1666235504333,"content":"jrm,今天的天气穿什么衣服合适啊","title":"jrm,今天的天气穿什么衣服合适啊","description":"no description yet","like_count":1,"comment_count":4,"view_count":279,"type":"post","tag":"not tag yet","imageList":"","content_source":null,"comments":[{"id":172141,"parent_id":45191,"type":1,"commentor":6532,"gmtCreate":null,"gmtModified":null,"like_count":4,"content":"短裤和羽绒服","anonymity":0,"any_name":null,"commentCount":null,"user":{"id":6532,"name":"超究极战士不破咲","avatar_url":"http://test01-20200725.oss-cn-shenzhen.aliyuncs.com/image/1666112431342.jpg?Expires=1981472424&OSSAccessKeyId=LTAI4G5RL7pjavqASCwc42kR&Signature=bUPigbqegqaztJ3ia3CoKgDni2c%3D"},"isCommentLike":-5,"dislike_count":0},{"id":172140,"parent_id":45191,"type":1,"commentor":10582,"gmtCreate":null,"gmtModified":null,"like_count":0,"content":"裸奔","anonymity":1,"any_name":"哥斯拉","commentCount":null,"user":{"id":10582,"name":"U_68191666097","avatar_url":null},"isCommentLike":-5,"dislike_count":0},{"id":172163,"parent_id":45191,"type":1,"commentor":10351,"gmtCreate":null,"gmtModified":null,"like_count":0,"content":"一件卫衣差不多啦","anonymity":1,"any_name":"亚古兽","commentCount":null,"user":{"id":10351,"name":"3663916342","avatar_url":null},"isCommentLike":-5,"dislike_count":0},{"id":172168,"parent_id":45191,"type":1,"commentor":9613,"gmtCreate":null,"gmtModified":null,"like_count":0,"content":"品如的衣服","anonymity":0,"any_name":null,"commentCount":null,"user":{"id":9613,"name":"背包。","avatar_url":"http://test01-20200725.oss-cn-shenzhen.aliyuncs.com/image/1665414579737.jpg?Expires=1980774572&OSSAccessKeyId=LTAI4G5RL7pjavqASCwc42kR&Signature=WFm22S6iHaosKJFKZwK%2FhIVT%2BFU%3D"},"isCommentLike":-5,"dislike_count":0}],"any_name":"Anton","relation":-2,"liked":-4,"anonymity":1,"dislike_count":0}