{"id":45500,"author":null,"author_avatar_url":null,"author_id":6937,"author_status":1,"gmt_create":1666329891449,"gmt_modified":1666329891449,"content":"为了学业扭曲成卑微的形状、、\n赶紧毕业吧","title":"为了学业扭曲成卑微的形状、、\n赶紧毕业吧","description":"no description yet","like_count":1,"comment_count":1,"view_count":97,"type":"post","tag":"not tag yet","imageList":"","content_source":null,"comments":[{"id":173260,"parent_id":45500,"type":1,"commentor":6937,"gmtCreate":null,"gmtModified":null,"like_count":0,"content":"srds，但，以后打工的时候依旧会扭曲成卑微的形状、、我好恨这个b社会","anonymity":1,"any_name":"Jerry","commentCount":null,"user":{"id":6937,"name":"-----","avatar_url":null},"isCommentLike":-5,"dislike_count":0}],"any_name":"Jerry","relation":-2,"liked":-4,"anonymity":1,"dislike_count":0}