{"id":47650,"author":null,"author_avatar_url":null,"author_id":2036,"author_status":1,"gmt_create":1667022975365,"gmt_modified":1667022975365,"content":"那些问从拱北过关可不可以的同学\n想一想那么多人都住在珠海拱北那边来学校","title":"那些问从拱北过关可不可以的同学\n想一想那么多人都住在珠海拱北那边来学校","description":"no description yet","like_count":0,"comment_count":1,"view_count":145,"type":"post","tag":"not tag yet","imageList":"","content_source":null,"comments":[{"id":181776,"parent_id":47650,"type":1,"commentor":7920,"gmtCreate":null,"gmtModified":null,"like_count":0,"content":"脾气真好兄弟","anonymity":1,"any_name":"老板","commentCount":null,"user":{"id":7920,"name":"U_324161652264","avatar_url":null},"isCommentLike":-5,"dislike_count":0}],"any_name":"内卷狂魔","relation":-2,"liked":-4,"anonymity":1,"dislike_count":0}