{"id":5022,"author":null,"author_avatar_url":null,"author_id":1609,"author_status":1,"gmt_create":1637478562813,"gmt_modified":1637478562813,"content":"不想回宿舍 或者 只想一个人呆在宿舍\n\uD83E\uDD72\uD83E\uDD72\uD83E\uDD72\uD83E\uDD72","title":"不想回宿舍 或者 只想一个人呆在宿舍\n\uD83E\uDD72\uD83E\uDD72\uD83E\uDD72\uD83E\uDD72","description":"no description yet","like_count":4,"comment_count":5,"view_count":177,"type":"post","tag":"not tag yet","imageList":"","content_source":null,"comments":[{"id":18288,"parent_id":5022,"type":1,"commentor":1295,"gmtCreate":null,"gmtModified":null,"like_count":0,"content":"我也是！\uD83E\uDD1D","anonymity":1,"any_name":"人生的智慧","commentCount":null,"user":{"id":1295,"name":"U_637031633831","avatar_url":null},"isCommentLike":-5,"dislike_count":0},{"id":18298,"parent_id":5022,"type":1,"commentor":773,"gmtCreate":null,"gmtModified":null,"like_count":0,"content":"我也是","anonymity":1,"any_name":"皮卡丘","commentCount":null,"user":{"id":773,"name":"바보","avatar_url":"https://thirdwx.qlogo.cn/mmopen/vi_32/ibib6xictyJOE94mYiaD7UO4rO6XSuQ1yib9DiccCiamhAjKjaez8kNJibqftVPBKO588aVP8ad6ZsIgwfoOH5BGx12Elg/132"},"isCommentLike":-5,"dislike_count":0},{"id":18307,"parent_id":5022,"type":1,"commentor":1232,"gmtCreate":null,"gmtModified":null,"like_count":0,"content":"我也是","anonymity":1,"any_name":"出前一丁","commentCount":null,"user":{"id":1232,"name":"U_511131633127","avatar_url":null},"isCommentLike":-5,"dislike_count":0},{"id":18308,"parent_id":5022,"type":1,"commentor":1048,"gmtCreate":null,"gmtModified":null,"like_count":0,"content":"本宫也是","anonymity":0,"any_name":null,"commentCount":null,"user":{"id":1048,"name":"Mxmtoon","avatar_url":"https://thirdwx.qlogo.cn/mmopen/vi_32/BgX1Kn6uGTJEd2EPsoR4dR9DUD9bOlSwHiae2D9R6ic78Hgqny8guZR5ibia8ua2xiajYjQkV54KJpnianxtd33deIkg/132"},"isCommentLike":-5,"dislike_count":0},{"id":18323,"parent_id":5022,"type":1,"commentor":1232,"gmtCreate":null,"gmtModified":null,"like_count":0,"content":"hi驯马女","anonymity":1,"any_name":"出前一丁","commentCount":null,"user":{"id":1232,"name":"U_511131633127","avatar_url":null},"isCommentLike":-5,"dislike_count":0}],"any_name":"和味牛杂","relation":-2,"liked":-4,"anonymity":1,"dislike_count":0}