{"id":6040,"author":null,"author_avatar_url":null,"author_id":592,"author_status":1,"gmt_create":1638429601288,"gmt_modified":1638429601288,"content":"家人们，学校给我们的那个email账号去哪里才能看到？","title":"家人们，学校给我们的那个email账号去哪里才能看到？","description":"no description yet","like_count":0,"comment_count":5,"view_count":96,"type":"post","tag":"not tag yet","imageList":"","content_source":null,"comments":[{"id":22566,"parent_id":6040,"type":1,"commentor":1295,"gmtCreate":null,"gmtModified":null,"like_count":0,"content":"下载outlook客户端","anonymity":1,"any_name":"GRE精选","commentCount":null,"user":{"id":1295,"name":"U_637031633831","avatar_url":null},"isCommentLike":-5,"dislike_count":0},{"id":22580,"parent_id":22566,"type":2,"commentor":592,"gmtCreate":null,"gmtModified":null,"like_count":0,"content":"然后呢\uD83D\uDE2D","anonymity":1,"any_name":"咖哩鱼蛋","commentCount":null,"user":{"id":592,"name":"xxl","avatar_url":"http://test01-20200725.oss-cn-shenzhen.aliyuncs.com/image/1664352859085.jpg?Expires=1979712854&OSSAccessKeyId=LTAI4G5RL7pjavqASCwc42kR&Signature=jqrJUes41AT1wXmBa32L8fBdjCs%3D"},"isCommentLike":-5,"dislike_count":0},{"id":22583,"parent_id":22580,"type":2,"commentor":1295,"gmtCreate":null,"gmtModified":null,"like_count":0,"content":"就可以登陆了呀","anonymity":1,"any_name":"GRE精选","commentCount":null,"user":{"id":1295,"name":"U_637031633831","avatar_url":null},"isCommentLike":-5,"dislike_count":0},{"id":22584,"parent_id":22580,"type":2,"commentor":1295,"gmtCreate":null,"gmtModified":null,"like_count":0,"content":"啊 你指的是要看账号吗？就是学号+student.must.edu.mo就是账户呀 密码是当初wemust密码","anonymity":1,"any_name":"GRE精选","commentCount":null,"user":{"id":1295,"name":"U_637031633831","avatar_url":null},"isCommentLike":-5,"dislike_count":0},{"id":22585,"parent_id":22584,"type":2,"commentor":592,"gmtCreate":null,"gmtModified":null,"like_count":0,"content":"哦哦好！非常感谢","anonymity":1,"any_name":"咖哩鱼蛋","commentCount":null,"user":{"id":592,"name":"xxl","avatar_url":"http://test01-20200725.oss-cn-shenzhen.aliyuncs.com/image/1664352859085.jpg?Expires=1979712854&OSSAccessKeyId=LTAI4G5RL7pjavqASCwc42kR&Signature=jqrJUes41AT1wXmBa32L8fBdjCs%3D"},"isCommentLike":-5,"dislike_count":0}],"any_name":"咖哩鱼蛋","relation":-2,"liked":-4,"anonymity":1,"dislike_count":0}