{"id":13797,"author":null,"author_avatar_url":null,"author_id":1628,"author_status":1,"gmt_create":1647254461377,"gmt_modified":1647254461377,"content":"请问严鸿基老师的ob 期中考试有大题吗，难度咋样","title":"请问严鸿基老师的ob 期中考试有大题吗，难度咋样","description":"no description yet","like_count":0,"comment_count":2,"view_count":121,"type":"post","tag":"not tag yet","imageList":"","content_source":null,"comments":[{"id":51285,"parent_id":13797,"type":1,"commentor":891,"gmtCreate":null,"gmtModified":null,"like_count":0,"content":"蹲一个","anonymity":0,"any_name":null,"commentCount":null,"user":{"id":891,"name":"王大王（动森打工版）","avatar_url":"https://thirdwx.qlogo.cn/mmopen/vi_32/Q0j4TwGTfTL72YEQthvp6YS76yVSRTJliaR7hGIqwsGCXyicicPEdQfOrmkqXQukW4HG3p2P9JCOWLQicRPIFv5k7A/132"},"isCommentLike":-5,"dislike_count":0},{"id":51291,"parent_id":13797,"type":1,"commentor":2480,"gmtCreate":null,"gmtModified":null,"like_count":0,"content":"有案例分析还有简答题","anonymity":1,"any_name":"亚古兽","commentCount":null,"user":{"id":2480,"name":"U_696701642132","avatar_url":null},"isCommentLike":-5,"dislike_count":0}],"any_name":"三鲜水饺","relation":-2,"liked":-4,"anonymity":1,"dislike_count":0}