{"id":19659,"author":null,"author_avatar_url":null,"author_id":787,"author_status":1,"gmt_create":1651041872976,"gmt_modified":1651041872976,"content":"选课wemust有每个年级的时间和专业课表和选修课表\n办签注续签每年学校会发一次在学证明 不需要自己花钱申请 注意最新通知 记得更新自己通行证资料 去年九月更新过的也要再提交一次 第一轮结束了 第二轮要求在3.31-5.4之间提交一次\n选课可以多问问 但是要明白最后都是 能进去再说 而且进去有啥抢啥 抢不到就没得挑了\n学会自己获取资讯","title":"选课wemust有每个年级的时间和专业课表和选修课表\n办签注续签每年学校会发一次在学证明 不需要自己花钱申请 注意最新通知 记得更新自己通行证资料 去年九月更新过的也要再","description":"no description yet","like_count":10,"comment_count":2,"view_count":254,"type":"post","tag":"not tag yet","imageList":"","content_source":null,"comments":[{"id":74190,"parent_id":19659,"type":1,"commentor":787,"gmtCreate":null,"gmtModified":null,"like_count":4,"content":"选修 ：跨学院两个 通识三个类别各一个 体育一个\n资讯科技演讲与辩论由不得你选分配好的\n自己要上的课在coes学习计划里都有 课程介绍官网进入每个学院 课程里面都有 还是说 学会看官网自己获取资讯","anonymity":1,"any_name":"喷火龙","commentCount":null,"user":{"id":787,"name":"U_496491631201","avatar_url":null},"isCommentLike":-5,"dislike_count":0},{"id":74211,"parent_id":19659,"type":1,"commentor":1451,"gmtCreate":null,"gmtModified":null,"like_count":0,"content":"建议搞一个置顶 再问就真的讨骂了","anonymity":1,"any_name":"哈士奇","commentCount":null,"user":{"id":1451,"name":"嘿\uD83C\uDE51️","avatar_url":"http://test01-20200725.oss-cn-shenzhen.aliyuncs.com/image/1656346717487.gif?Expires=1971706745&OSSAccessKeyId=LTAI4G5RL7pjavqASCwc42kR&Signature=%2FNnQl70m9ws2SDcg1yGogtguiiw%3D"},"isCommentLike":-5,"dislike_count":0}],"any_name":"喷火龙","relation":-2,"liked":-4,"anonymity":1,"dislike_count":0}