{"id":21591,"author":null,"author_avatar_url":null,"author_id":4489,"author_status":1,"gmt_create":1652119138324,"gmt_modified":1652119138324,"content":"我想问问，抢不到课会有啥后果","title":"我想问问，抢不到课会有啥后果","description":"no description yet","like_count":0,"comment_count":1,"view_count":110,"type":"post","tag":"not tag yet","imageList":"","content_source":null,"comments":[{"id":80621,"parent_id":21591,"type":1,"commentor":1925,"gmtCreate":null,"gmtModified":null,"like_count":0,"content":"不会有啥吧，只要在四年内修完就行","anonymity":1,"any_name":"亚古兽","commentCount":null,"user":{"id":1925,"name":"芒果好吃","avatar_url":"http://test01-20200725.oss-cn-shenzhen.aliyuncs.com/image/1638114699747.jpg?Expires=1953474692&OSSAccessKeyId=LTAI4G5RL7pjavqASCwc42kR&Signature=yod8uyMkcFxCR5GsMyuz2rCUv3w%3D"},"isCommentLike":-5,"dislike_count":0}],"any_name":"阿拉斯加猪","relation":-2,"liked":-4,"anonymity":1,"dislike_count":0}