{"id":22606,"author":null,"author_avatar_url":null,"author_id":635,"author_status":1,"gmt_create":1652451241567,"gmt_modified":1652451241567,"content":"我怕被人笑话，更怕没人看我呀","title":"我怕被人笑话，更怕没人看我呀","description":"no description yet","like_count":0,"comment_count":1,"view_count":5,"type":"post","tag":"not tag yet","imageList":"","content_source":null,"comments":[{"id":83692,"parent_id":22606,"type":1,"commentor":860,"gmtCreate":null,"gmtModified":null,"like_count":0,"content":"别想太多，你开心最重要！","anonymity":1,"any_name":"允指原味鸡","commentCount":null,"user":{"id":860,"name":"阿白","avatar_url":"https://thirdwx.qlogo.cn/mmopen/vi_32/Q3auHgzwzM4MqpUoS1JKlPFImtysjVUYbb0H8xnGUtCjndV1ic50MXC42ncuc0fH75suc5oBC4IyEfmO6sEWibRQ/132"},"isCommentLike":-5,"dislike_count":0}],"any_name":"Kelly","relation":-2,"liked":-4,"anonymity":1,"dislike_count":0}