{"id":23775,"author":null,"author_avatar_url":null,"author_id":1111,"author_status":1,"gmt_create":1652929361074,"gmt_modified":1652929361074,"content":"自习室啥时候收东西啊，为啥现在还有人晚上把东西放着就走啊\uD83D\uDE22","title":"自习室啥时候收东西啊，为啥现在还有人晚上把东西放着就走啊\uD83D\uDE22","description":"no description yet","like_count":0,"comment_count":2,"view_count":148,"type":"post","tag":"not tag yet","imageList":"","content_source":null,"comments":[{"id":87667,"parent_id":23775,"type":1,"commentor":1056,"gmtCreate":null,"gmtModified":null,"like_count":0,"content":"没办法 我不放别人就会放 但是我是会第二天八点多就来的","anonymity":1,"any_name":"Jerry","commentCount":null,"user":{"id":1056,"name":"Jane","avatar_url":"http://test01-20200725.oss-cn-shenzhen.aliyuncs.com/image/1667009343942.jpg?Expires=1982369342&OSSAccessKeyId=LTAI4G5RL7pjavqASCwc42kR&Signature=S3iKcssDln8g%2FX%2F7iY27oZ35PgE%3D"},"isCommentLike":-5,"dislike_count":0},{"id":87695,"parent_id":87667,"type":2,"commentor":6334,"gmtCreate":null,"gmtModified":null,"like_count":0,"content":"我也素","anonymity":1,"any_name":"四川麻辣烫","commentCount":null,"user":{"id":6334,"name":"U_98991649602","avatar_url":null},"isCommentLike":-5,"dislike_count":0}],"any_name":"摆烂到底","relation":-2,"liked":-4,"anonymity":1,"dislike_count":0}