{"id":26206,"author":null,"author_avatar_url":null,"author_id":1074,"author_status":1,"gmt_create":1654094419904,"gmt_modified":1654094419904,"content":"有上暑假课的大二姐妹吗","title":"有上暑假课的大二姐妹吗","description":"no description yet","like_count":1,"comment_count":1,"view_count":143,"type":"post","tag":"not tag yet","imageList":"","content_source":null,"comments":[{"id":96015,"parent_id":26206,"type":1,"commentor":7803,"gmtCreate":null,"gmtModified":null,"like_count":0,"content":"这里","anonymity":1,"any_name":"芋圆奶茶","commentCount":null,"user":{"id":7803,"name":"U_211261652170","avatar_url":"http://test01-20200725.oss-cn-shenzhen.aliyuncs.com/image/1657384355846.jpg?Expires=1972744354&OSSAccessKeyId=LTAI4G5RL7pjavqASCwc42kR&Signature=ah0m%2BJJokvPENelJ%2FY8hy87%2Fszs%3D"},"isCommentLike":-5,"dislike_count":0}],"any_name":"深海鳕鱼堡","relation":-2,"liked":-4,"anonymity":1,"dislike_count":0}