{"id":38275,"author":null,"author_avatar_url":null,"author_id":9156,"author_status":1,"gmt_create":1663210874519,"gmt_modified":1663210874519,"content":"悄悄问一下  敖子逸今天来线下课了没","title":"悄悄问一下  敖子逸今天来线下课了没","description":"no description yet","like_count":3,"comment_count":4,"view_count":819,"type":"post","tag":"not tag yet","imageList":"","content_source":null,"comments":[{"id":146828,"parent_id":38275,"type":1,"commentor":367,"gmtCreate":null,"gmtModified":null,"like_count":9,"content":"呃 其实不用在意的","anonymity":1,"any_name":"Jerry","commentCount":null,"user":{"id":367,"name":"就叫xuan","avatar_url":"https://thirdwx.qlogo.cn/mmopen/vi_32/Q0j4TwGTfTJEJRSdJQXTwYW5yCGicTGt1vnJt7JUMFmeHRDAUqoHWmulBoLyKtpKZs5hgxC54YJs0NZdIWl3iaaQ/132"},"isCommentLike":-5,"dislike_count":0},{"id":146827,"parent_id":38275,"type":1,"commentor":9375,"gmtCreate":null,"gmtModified":null,"like_count":4,"content":"科大没他开不了课捏","anonymity":1,"any_name":"珠海小天使","commentCount":null,"user":{"id":9375,"name":"U_447561658214","avatar_url":null},"isCommentLike":-5,"dislike_count":0},{"id":146844,"parent_id":38275,"type":1,"commentor":1488,"gmtCreate":null,"gmtModified":null,"like_count":3,"content":"敖子逸昨天还有飞机的行程飞去其他地方呢hhhhh 当然没来","anonymity":1,"any_name":"拉面小路","commentCount":null,"user":{"id":1488,"name":"la","avatar_url":"http://test01-20200725.oss-cn-shenzhen.aliyuncs.com/image/1664853097119.jpg?Expires=1980213088&OSSAccessKeyId=LTAI4G5RL7pjavqASCwc42kR&Signature=oeYsfC3l6p%2BW%2F0r4Uh1lBSRhw%2FE%3D"},"isCommentLike":-5,"dislike_count":0},{"id":146860,"parent_id":38275,"type":1,"commentor":9164,"gmtCreate":null,"gmtModified":null,"like_count":1,"content":"他爱来不来","anonymity":1,"any_name":"拱北快递员","commentCount":null,"user":{"id":9164,"name":"U_19463826","avatar_url":null},"isCommentLike":-5,"dislike_count":0}],"any_name":"微积分","relation":-2,"liked":-4,"anonymity":1,"dislike_count":0}