{"id":47260,"author":null,"author_avatar_url":null,"author_id":129,"author_status":1,"gmt_create":1666879319076,"gmt_modified":1666879319076,"content":"有些男的能不能别这么普\uD83E\uDD2D聊骚聊到有男朋友的女生被拒了还沾沾自喜到处宣传？你的人生好悲惨","title":"有些男的能不能别这么普\uD83E\uDD2D聊骚聊到有男朋友的女生被拒了还沾沾自喜到处宣传？你的人生好悲惨","description":"no description yet","like_count":2,"comment_count":1,"view_count":107,"type":"post","tag":"not tag yet","imageList":"","content_source":null,"comments":[{"id":180258,"parent_id":47260,"type":1,"commentor":10415,"gmtCreate":null,"gmtModified":null,"like_count":0,"content":"赞一个","anonymity":1,"any_name":"摆烂到底","commentCount":null,"user":{"id":10415,"name":"哈哈哈哈有病吧","avatar_url":null},"isCommentLike":-5,"dislike_count":0}],"any_name":"哈士奇","relation":-2,"liked":-4,"anonymity":1,"dislike_count":0}