{"id":51959,"author":null,"author_avatar_url":null,"author_id":4630,"author_status":1,"gmt_create":1668301998555,"gmt_modified":1668301998555,"content":"请问没登记疫苗的情况下，今天晚上十点珠海回澳门回得来吗","title":"请问没登记疫苗的情况下，今天晚上十点珠海回澳门回得来吗","description":"no description yet","like_count":0,"comment_count":1,"view_count":155,"type":"post","tag":"not tag yet","imageList":"http://test01-20200725.oss-cn-shenzhen.aliyuncs.com/image/1668301971034.jpg?Expires=1983661962&OSSAccessKeyId=LTAI4G5RL7pjavqASCwc42kR&Signature=21%2F4SCM7gRAqozPikGgcKgt%2BG%2Bc%3D","content_source":null,"comments":[{"id":196607,"parent_id":51959,"type":1,"commentor":1295,"gmtCreate":null,"gmtModified":null,"like_count":1,"content":"今天可以走自助，明天也可，就要走人工了","anonymity":1,"any_name":"Kelly","commentCount":null,"user":{"id":1295,"name":"U_637031633831","avatar_url":null},"isCommentLike":-5,"dislike_count":0}],"any_name":"和味牛杂","relation":-2,"liked":-4,"anonymity":1,"dislike_count":0}