{"id":53255,"author":null,"author_avatar_url":null,"author_id":10247,"author_status":1,"gmt_create":1668677772358,"gmt_modified":1668677772358,"content":"我想吃正宗一点的沙县小吃！！\n能不能来个人推荐一下\uD83E\uDD2F\uD83E\uDD2F","title":"我想吃正宗一点的沙县小吃！！\n能不能来个人推荐一下\uD83E\uDD2F\uD83E\uDD2F","description":"no description yet","like_count":0,"comment_count":0,"view_count":3,"type":"post","tag":"not tag yet","imageList":"","content_source":null,"comments":null,"any_name":"多喝热水","relation":-2,"liked":-4,"anonymity":1,"dislike_count":0}