{"id":54710,"author":null,"author_avatar_url":null,"author_id":1295,"author_status":1,"gmt_create":1669169717241,"gmt_modified":1669169717241,"content":"我们学校饭堂的食品来源可靠吗？我本来心理作用就特别重……昨天在点聚吃了份肉沫豆腐，碰上很大一块肉，心理作用担心它没熟，可是又不想浪费，加上它是我那顿唯一的肉类，就告诉自己饭堂应该还是会比较注意的，别胡思乱想。但是老觉得那猪肉挺嫩的甚至有点点红……吃完以后担心了很久怕有寄生虫……怕不熟，也怕那肉没经过检疫啥的有虫卵什么的……","title":"我们学校饭堂的食品来源可靠吗？我本来心理作用就特别重……昨天在点聚吃了份肉沫豆腐，碰上很大一块肉，心理作用担心它没熟，可是又不想浪费，加上它是我那顿唯一的肉类，就告诉自己","description":"no description yet","like_count":2,"comment_count":12,"view_count":331,"type":"post","tag":"not tag yet","imageList":"","content_source":null,"comments":[{"id":205878,"parent_id":54710,"type":1,"commentor":10712,"gmtCreate":null,"gmtModified":null,"like_count":2,"content":"学校的食堂是私立私人承包的 赚钱为主 在想什么呢","anonymity":1,"any_name":"咖哩鱼蛋","commentCount":null,"user":{"id":10712,"name":"U_17981666767","avatar_url":null},"isCommentLike":-5,"dislike_count":0},{"id":205821,"parent_id":54710,"type":1,"commentor":8416,"gmtCreate":null,"gmtModified":null,"like_count":0,"content":"对电锯是经常这样，而且有的腥味特别重","anonymity":1,"any_name":"皮卡丘","commentCount":null,"user":{"id":8416,"name":"nicheng","avatar_url":null},"isCommentLike":-5,"dislike_count":0},{"id":205822,"parent_id":54710,"type":1,"commentor":8416,"gmtCreate":null,"gmtModified":null,"like_count":0,"content":"不是很清楚可不可靠，不知道可不可以要求公开","anonymity":1,"any_name":"皮卡丘","commentCount":null,"user":{"id":8416,"name":"nicheng","avatar_url":null},"isCommentLike":-5,"dislike_count":0},{"id":205838,"parent_id":54710,"type":1,"commentor":8509,"gmtCreate":null,"gmtModified":null,"like_count":0,"content":"点聚看着还行，吃起来真纳闷咋那么不好吃滴\uD83D\uDE2D\uD83D\uDE2D","anonymity":1,"any_name":"允指原味鸡","commentCount":null,"user":{"id":8509,"name":"U_523941652864","avatar_url":null},"isCommentLike":-5,"dislike_count":0},{"id":205857,"parent_id":205821,"type":2,"commentor":1295,"gmtCreate":null,"gmtModified":null,"like_count":0,"content":"是呀，这次是后悔了，以后不放心就不吃了，点聚的好吃不到哪里去\uD83E\uDD72","anonymity":1,"any_name":"英国短毛猫","commentCount":null,"user":{"id":1295,"name":"U_637031633831","avatar_url":null},"isCommentLike":-5,"dislike_count":0},{"id":205859,"parent_id":205838,"type":2,"commentor":1295,"gmtCreate":null,"gmtModified":null,"like_count":0,"content":"是的，我是为了省钱几乎都去点聚不吃厨艺天地，但是老吃点聚真的吃不下去了\uD83E\uDD72味道好不到哪里去","anonymity":1,"any_name":"英国短毛猫","commentCount":null,"user":{"id":1295,"name":"U_637031633831","avatar_url":null},"isCommentLike":-5,"dislike_count":0},{"id":205862,"parent_id":205857,"type":2,"commentor":8416,"gmtCreate":null,"gmtModified":null,"like_count":0,"content":"电锯单独点餐的饭我觉得还可以，量也不错，可以尝试一下","anonymity":1,"any_name":"皮卡丘","commentCount":null,"user":{"id":8416,"name":"nicheng","avatar_url":null},"isCommentLike":-5,"dislike_count":0},{"id":205884,"parent_id":205878,"type":2,"commentor":1295,"gmtCreate":null,"gmtModified":null,"like_count":0,"content":"哎，他们都是赢利为主，估计都不会重视食材质量安全问题的……","anonymity":1,"any_name":"英国短毛猫","commentCount":null,"user":{"id":1295,"name":"U_637031633831","avatar_url":null},"isCommentLike":-5,"dislike_count":0},{"id":205885,"parent_id":205862,"type":2,"commentor":1295,"gmtCreate":null,"gmtModified":null,"like_count":0,"content":"好的！谢谢推荐，我下次试一下","anonymity":1,"any_name":"英国短毛猫","commentCount":null,"user":{"id":1295,"name":"U_637031633831","avatar_url":null},"isCommentLike":-5,"dislike_count":0},{"id":205998,"parent_id":205878,"type":2,"commentor":10712,"gmtCreate":null,"gmtModified":null,"like_count":0,"content":"肯定啊 肯定啊是就知道涨价 呕","anonymity":1,"any_name":"网瘾少年","commentCount":null,"user":{"id":10712,"name":"U_17981666767","avatar_url":null},"isCommentLike":-5,"dislike_count":0},{"id":206224,"parent_id":205859,"type":2,"commentor":8416,"gmtCreate":null,"gmtModified":null,"like_count":0,"content":"如果有自己炒菜或者点外卖剩了菜去电锯买饭和汤是比较划算啦。菜真的是没有一个很好吃的","anonymity":1,"any_name":"皮卡丘","commentCount":null,"user":{"id":8416,"name":"nicheng","avatar_url":null},"isCommentLike":-5,"dislike_count":0},{"id":206225,"parent_id":205885,"type":2,"commentor":8416,"gmtCreate":null,"gmtModified":null,"like_count":0,"content":"不客气","anonymity":1,"any_name":"皮卡丘","commentCount":null,"user":{"id":8416,"name":"nicheng","avatar_url":null},"isCommentLike":-5,"dislike_count":0}],"any_name":"英国短毛猫","relation":-2,"liked":-4,"anonymity":1,"dislike_count":0}