{"id":55179,"author":null,"author_avatar_url":null,"author_id":6894,"author_status":1,"gmt_create":1669285364199,"gmt_modified":1669285364199,"content":"有想参加校园创新创业大赛的同学吗？","title":"有想参加校园创新创业大赛的同学吗？","description":"no description yet","like_count":0,"comment_count":8,"view_count":74,"type":"post","tag":"not tag yet","imageList":"","content_source":null,"comments":[{"id":207789,"parent_id":55179,"type":1,"commentor":8200,"gmtCreate":null,"gmtModified":null,"like_count":0,"content":"1111我可以吗 我有全国创新的省赛奖","anonymity":0,"any_name":null,"commentCount":null,"user":{"id":8200,"name":"U_602501652758","avatar_url":null},"isCommentLike":-5,"dislike_count":0},{"id":207791,"parent_id":55179,"type":1,"commentor":1736,"gmtCreate":null,"gmtModified":null,"like_count":0,"content":"抗御味啊 挨踢人去伤赛还能拿奖","anonymity":1,"any_name":"和味牛杂","commentCount":null,"user":{"id":1736,"name":"灵魂小酱汁","avatar_url":"http://test01-20200725.oss-cn-shenzhen.aliyuncs.com/image/1637055972210.jpg?Expires=1952415967&OSSAccessKeyId=LTAI4G5RL7pjavqASCwc42kR&Signature=K%2FKqibg6npytO%2Bbk%2BHf9EqY818s%3D"},"isCommentLike":-5,"dislike_count":0},{"id":207802,"parent_id":207789,"type":2,"commentor":10672,"gmtCreate":null,"gmtModified":null,"like_count":0,"content":"可以带我一个吗","anonymity":1,"any_name":"布偶猫","commentCount":null,"user":{"id":10672,"name":"U_842321666541","avatar_url":null},"isCommentLike":-5,"dislike_count":0},{"id":207812,"parent_id":207789,"type":2,"commentor":6894,"gmtCreate":null,"gmtModified":null,"like_count":0,"content":"可以加微信聊聊嘛","anonymity":1,"any_name":"拉面小路","commentCount":null,"user":{"id":6894,"name":"U_235931650794","avatar_url":null},"isCommentLike":-5,"dislike_count":0},{"id":207816,"parent_id":207812,"type":2,"commentor":8200,"gmtCreate":null,"gmtModified":null,"like_count":0,"content":"15985703050","anonymity":0,"any_name":null,"commentCount":null,"user":{"id":8200,"name":"U_602501652758","avatar_url":null},"isCommentLike":-5,"dislike_count":0},{"id":207937,"parent_id":207789,"type":2,"commentor":9685,"gmtCreate":null,"gmtModified":null,"like_count":0,"content":"可以一起不","anonymity":0,"any_name":null,"commentCount":null,"user":{"id":9685,"name":"Ultimate","avatar_url":null},"isCommentLike":-5,"dislike_count":0},{"id":209270,"parent_id":207937,"type":2,"commentor":6894,"gmtCreate":null,"gmtModified":null,"like_count":0,"content":"朋友是大几的？什么专业的？可以留v聊聊吗？","anonymity":0,"any_name":null,"commentCount":null,"user":{"id":6894,"name":"U_235931650794","avatar_url":null},"isCommentLike":-5,"dislike_count":0},{"id":216027,"parent_id":209270,"type":2,"commentor":9685,"gmtCreate":null,"gmtModified":null,"like_count":0,"content":"大三中医学","anonymity":0,"any_name":null,"commentCount":null,"user":{"id":9685,"name":"Ultimate","avatar_url":null},"isCommentLike":-5,"dislike_count":0}],"any_name":"拉面小路","relation":-2,"liked":-4,"anonymity":1,"dislike_count":0}