{"id":55789,"author":"最后一根稻草","author_avatar_url":null,"author_id":11191,"author_status":1,"gmt_create":1669434339864,"gmt_modified":1669434339864,"content":"想问一下如果zoom网课上着上着退出去了 重新进入会重新算进入会议的时间吗","title":"想问一下如果zoom网课上着上着退出去了 重新进入会重新算进入会议的时间吗","description":"no description yet","like_count":0,"comment_count":2,"view_count":99,"type":"post","tag":"not tag yet","imageList":"","content_source":null,"comments":[{"id":210101,"parent_id":55789,"type":1,"commentor":10347,"gmtCreate":null,"gmtModified":null,"like_count":0,"content":"应该不会吧  wemust上写的是第一次进入的时间\n我之前上课一直反复掉线好像没什么影响","anonymity":1,"any_name":"珠海小天使","commentCount":null,"user":{"id":10347,"name":"dfyjbgy","avatar_url":"http://test01-20200725.oss-cn-shenzhen.aliyuncs.com/image/1668569097922.jpg?Expires=1983929091&OSSAccessKeyId=LTAI4G5RL7pjavqASCwc42kR&Signature=yaVJ5wWGXX1yvXRRdyYINPXXLMc%3D"},"isCommentLike":-5,"dislike_count":0},{"id":210109,"parent_id":210101,"type":2,"commentor":11191,"gmtCreate":null,"gmtModified":null,"like_count":0,"content":"谢谢","anonymity":0,"any_name":null,"commentCount":null,"user":{"id":11191,"name":"最后一根稻草","avatar_url":null},"isCommentLike":-5,"dislike_count":0}],"any_name":null,"relation":-2,"liked":-4,"anonymity":0,"dislike_count":0}