{"id":56528,"author":null,"author_avatar_url":null,"author_id":1841,"author_status":1,"gmt_create":1669723619696,"gmt_modified":1669723619696,"content":"发现自己愚蠢至极，怎么办？","title":"发现自己愚蠢至极，怎么办？","description":"no description yet","like_count":0,"comment_count":2,"view_count":97,"type":"post","tag":"not tag yet","imageList":"","content_source":null,"comments":[{"id":212663,"parent_id":56528,"type":1,"commentor":11356,"gmtCreate":null,"gmtModified":null,"like_count":0,"content":"学习","anonymity":0,"any_name":null,"commentCount":null,"user":{"id":11356,"name":"用户77777777","avatar_url":"http://test01-20200725.oss-cn-shenzhen.aliyuncs.com/image/1669702125901.jpg?Expires=1985062124&OSSAccessKeyId=LTAI4G5RL7pjavqASCwc42kR&Signature=ldZvs%2FL1wH5KFAzcCw7Kww4TVaQ%3D"},"isCommentLike":-5,"dislike_count":0},{"id":212719,"parent_id":56528,"type":1,"commentor":8416,"gmtCreate":null,"gmtModified":null,"like_count":0,"content":"多看书","anonymity":1,"any_name":"拉面小路","commentCount":null,"user":{"id":8416,"name":"nicheng","avatar_url":null},"isCommentLike":-5,"dislike_count":0}],"any_name":"GRE精选","relation":-2,"liked":-4,"anonymity":1,"dislike_count":0}