{"id":59240,"author":null,"author_avatar_url":null,"author_id":11060,"author_status":1,"gmt_create":1670328565465,"gmt_modified":1670328565465,"content":"有没有同学选完课的 可以说一下新系统体验怎么样吗？","title":"有没有同学选完课的 可以说一下新系统体验怎么样吗？","description":"no description yet","like_count":1,"comment_count":3,"view_count":147,"type":"post","tag":"not tag yet","imageList":"","content_source":null,"comments":[{"id":221133,"parent_id":59240,"type":1,"commentor":784,"gmtCreate":null,"gmtModified":null,"like_count":0,"content":"大四的 我感觉很\uD83C\uDE51️","anonymity":0,"any_name":null,"commentCount":null,"user":{"id":784,"name":"越","avatar_url":"https://thirdwx.qlogo.cn/mmopen/vi_32/Q0j4TwGTfTLxHm0z7Rh5ONBwiagN2NAYg40QY4gLibscdWnN7Ypqf3VWaAA5zoziarEiayEXPpJNS4nwWnBU34u0hQ/132"},"isCommentLike":-5,"dislike_count":0},{"id":221137,"parent_id":221133,"type":2,"commentor":11060,"gmtCreate":null,"gmtModified":null,"like_count":0,"content":"就是不会出现进不去的现象了对吧","anonymity":1,"any_name":"大潭山车队","commentCount":null,"user":{"id":11060,"name":"U_505291668501","avatar_url":null},"isCommentLike":-5,"dislike_count":0},{"id":221138,"parent_id":221137,"type":2,"commentor":784,"gmtCreate":null,"gmtModified":null,"like_count":0,"content":"至少我们大家都很顺利 我了解到","anonymity":0,"any_name":null,"commentCount":null,"user":{"id":784,"name":"越","avatar_url":"https://thirdwx.qlogo.cn/mmopen/vi_32/Q0j4TwGTfTLxHm0z7Rh5ONBwiagN2NAYg40QY4gLibscdWnN7Ypqf3VWaAA5zoziarEiayEXPpJNS4nwWnBU34u0hQ/132"},"isCommentLike":-5,"dislike_count":0}],"any_name":"大潭山车队","relation":-2,"liked":-4,"anonymity":1,"dislike_count":0}