{"id":59268,"author":null,"author_avatar_url":null,"author_id":9640,"author_status":1,"gmt_create":1670331878607,"gmt_modified":1670331878607,"content":"有没有人知道新传的平均绩点的多少呀，回答的朋友都a+","title":"有没有人知道新传的平均绩点的多少呀，回答的朋友都a+","description":"no description yet","like_count":1,"comment_count":2,"view_count":204,"type":"post","tag":"not tag yet","imageList":"","content_source":null,"comments":[{"id":221189,"parent_id":59268,"type":1,"commentor":11383,"gmtCreate":null,"gmtModified":null,"like_count":0,"content":"同问","anonymity":1,"any_name":"出前一丁","commentCount":null,"user":{"id":11383,"name":"芝士就是知识","avatar_url":"http://test01-20200725.oss-cn-shenzhen.aliyuncs.com/image/1669774989591.jpg?Expires=1985134982&OSSAccessKeyId=LTAI4G5RL7pjavqASCwc42kR&Signature=QzKXmw2T0HFbJ0tUJqWddOtMV4M%3D"},"isCommentLike":-5,"dislike_count":0},{"id":221255,"parent_id":59268,"type":1,"commentor":11477,"gmtCreate":null,"gmtModified":null,"like_count":0,"content":"说平均没有什么参考性的，要看百分位","anonymity":1,"any_name":"深海鳕鱼堡","commentCount":null,"user":{"id":11477,"name":"流汁鸡腿排！","avatar_url":null},"isCommentLike":-5,"dislike_count":0}],"any_name":"珠海小天使","relation":-2,"liked":-4,"anonymity":1,"dislike_count":0}