{"id":60699,"author":"U_880311670662","author_avatar_url":null,"author_id":14240,"author_status":1,"gmt_create":1670662114753,"gmt_modified":1670662114753,"content":"问问家人们 圣诞节回家的多吗 \n要是阳了 转阴之后可以回学校考试吗\uD83E\uDD7A","title":"问问家人们 圣诞节回家的多吗 \n要是阳了 转阴之后可以回学校考试吗\uD83E\uDD7A","description":"no description yet","like_count":0,"comment_count":4,"view_count":143,"type":"post","tag":"not tag yet","imageList":"","content_source":null,"comments":[{"id":225494,"parent_id":60699,"type":1,"commentor":10336,"gmtCreate":null,"gmtModified":null,"like_count":0,"content":"救命救命同问，超急呜呜呜","anonymity":1,"any_name":"三鲜水饺","commentCount":null,"user":{"id":10336,"name":"U_345671665158","avatar_url":null},"isCommentLike":-5,"dislike_count":0},{"id":225497,"parent_id":60699,"type":1,"commentor":9578,"gmtCreate":null,"gmtModified":null,"like_count":0,"content":"同问","anonymity":1,"any_name":"英国短毛猫","commentCount":null,"user":{"id":9578,"name":"U_504571660219","avatar_url":null},"isCommentLike":-5,"dislike_count":0},{"id":225522,"parent_id":60699,"type":1,"commentor":1938,"gmtCreate":null,"gmtModified":null,"like_count":0,"content":"我也怕赶不回期末考\uD83D\uDE2D","anonymity":1,"any_name":"网瘾少年","commentCount":null,"user":{"id":1938,"name":"路环保卫队","avatar_url":"http://test01-20200725.oss-cn-shenzhen.aliyuncs.com/image/1638284305997.jpg?Expires=1953644296&OSSAccessKeyId=LTAI4G5RL7pjavqASCwc42kR&Signature=fEh0QaTBUq%2B%2BSzjISns77jSy81Q%3D"},"isCommentLike":-5,"dislike_count":0},{"id":225743,"parent_id":60699,"type":1,"commentor":189,"gmtCreate":null,"gmtModified":null,"like_count":0,"content":"感觉住珠海更容易\uD83D\uDC11啊\uD83D\uDE2D","anonymity":1,"any_name":"offer收割机","commentCount":null,"user":{"id":189,"name":"U_353061631109","avatar_url":null},"isCommentLike":-5,"dislike_count":0}],"any_name":null,"relation":-2,"liked":-4,"anonymity":0,"dislike_count":0}