{"id":62570,"author":null,"author_avatar_url":null,"author_id":9745,"author_status":1,"gmt_create":1670947158299,"gmt_modified":1670947158299,"content":"趁人多 问一下lhc的逻辑容易挂吗\uD83E\uDD72\uD83E\uDD72太多没写出来的了","title":"趁人多 问一下lhc的逻辑容易挂吗\uD83E\uDD72\uD83E\uDD72太多没写出来的了","description":"no description yet","like_count":1,"comment_count":2,"view_count":91,"type":"post","tag":"not tag yet","imageList":"","content_source":null,"comments":[{"id":229832,"parent_id":62570,"type":1,"commentor":1457,"gmtCreate":null,"gmtModified":null,"like_count":0,"content":"题不难，会就不挂","anonymity":1,"any_name":"阿拉斯加猪","commentCount":null,"user":{"id":1457,"name":"\uD83E\uDD8Booou","avatar_url":"https://thirdwx.qlogo.cn/mmopen/vi_32/U6tHjJxrtD3DUEfO2SsBwzbuG5hPgOMMT3eOgxhz7OCNm38yaocBADwMiaFhu8ryEHQHZKCErlnsnN6n5pT5Ihw/132"},"isCommentLike":-5,"dislike_count":0},{"id":229834,"parent_id":229832,"type":2,"commentor":9745,"gmtCreate":null,"gmtModified":null,"like_count":0,"content":"不会咋办","anonymity":1,"any_name":"Jerry","commentCount":null,"user":{"id":9745,"name":"流泪猫猫头","avatar_url":"http://test01-20200725.oss-cn-shenzhen.aliyuncs.com/image/1667755181696.jpg?Expires=1983115177&OSSAccessKeyId=LTAI4G5RL7pjavqASCwc42kR&Signature=RJtQsfoxHH1Kyakt43jXsL4puqQ%3D"},"isCommentLike":-5,"dislike_count":0}],"any_name":"Jerry","relation":-2,"liked":-4,"anonymity":1,"dislike_count":0}