{"id":62840,"author":"U_560651665490","author_avatar_url":null,"author_id":10381,"author_status":1,"gmt_create":1671004564819,"gmt_modified":1671004564819,"content":"现在点绽领抗疫包的人多吗","title":"现在点绽领抗疫包的人多吗","description":"no description yet","like_count":0,"comment_count":2,"view_count":97,"type":"post","tag":"not tag yet","imageList":"","content_source":null,"comments":[{"id":230624,"parent_id":62840,"type":1,"commentor":12082,"gmtCreate":null,"gmtModified":null,"like_count":0,"content":"多","anonymity":1,"any_name":"网瘾少年","commentCount":null,"user":{"id":12082,"name":"玖.","avatar_url":"https://thirdwx.qlogo.cn/mmopen/vi_32/FiaIr8Gdgq7IEnTh88cJPcOF5Tia6u3icUCHtx5pQMZE34zNmmAbTpZSa75nlqx4HQeX4kNia6ickfh1rES2Lgj8TYg/132"},"isCommentLike":-5,"dislike_count":0},{"id":230867,"parent_id":62840,"type":1,"commentor":950,"gmtCreate":null,"gmtModified":null,"like_count":0,"content":"第一天肯定人多，不急的话周五之前拿了就行","anonymity":1,"any_name":"微积分","commentCount":null,"user":{"id":950,"name":"嘉心糖今天吃什么","avatar_url":"http://test01-20200725.oss-cn-shenzhen.aliyuncs.com/image/1653601697278.gif?Expires=1968961688&OSSAccessKeyId=LTAI4G5RL7pjavqASCwc42kR&Signature=MJ1wFoThzUSd5vemDHpVKNWnCcA%3D"},"isCommentLike":-5,"dislike_count":0}],"any_name":null,"relation":-2,"liked":-4,"anonymity":0,"dislike_count":0}