{"id":64179,"author":null,"author_avatar_url":null,"author_id":9735,"author_status":1,"gmt_create":1671273858055,"gmt_modified":1671273858055,"content":"想问下学校有卖暖水袋吗","title":"想问下学校有卖暖水袋吗","description":"no description yet","like_count":0,"comment_count":2,"view_count":23,"type":"post","tag":"not tag yet","imageList":"","content_source":null,"comments":[{"id":234552,"parent_id":64179,"type":1,"commentor":49,"gmtCreate":null,"gmtModified":null,"like_count":0,"content":"潮集社有","anonymity":1,"any_name":"英国短毛猫","commentCount":null,"user":{"id":49,"name":"ia","avatar_url":"http://test01-20200725.oss-cn-shenzhen.aliyuncs.com/image/1668359398122.jpg?Expires=1983719388&OSSAccessKeyId=LTAI4G5RL7pjavqASCwc42kR&Signature=DJFey2ryDpIjcKI5qY0u2Mi%2BVEg%3D"},"isCommentLike":-5,"dislike_count":0},{"id":234683,"parent_id":234552,"type":2,"commentor":9735,"gmtCreate":null,"gmtModified":null,"like_count":0,"content":"好的谢谢","anonymity":1,"any_name":"英国短毛猫","commentCount":null,"user":{"id":9735,"name":"冬虫","avatar_url":null},"isCommentLike":-5,"dislike_count":0}],"any_name":"英国短毛猫","relation":-2,"liked":-4,"anonymity":1,"dislike_count":0}