{"id":8972,"author":null,"author_avatar_url":null,"author_id":1488,"author_status":1,"gmt_create":1641994204047,"gmt_modified":1641994204047,"content":"说了不经过脑子的话 现在无比后悔\n自己其实已经是说话之前会思考很多的人了\n但是还是避免不了有时候太冲动 会说出几句鲁莽的话\uD83D\uDE2D \n\uD83D\uDE2D \uD83D\uDE2D","title":"说了不经过脑子的话 现在无比后悔\n自己其实已经是说话之前会思考很多的人了\n但是还是避免不了有时候太冲动 会说出几句鲁莽的话\uD83D\uDE2D \n\uD83D\uDE2D \uD83D\uDE2D","description":"no description yet","like_count":1,"comment_count":1,"view_count":28,"type":"post","tag":"not tag yet","imageList":"","content_source":null,"comments":[{"id":32998,"parent_id":8972,"type":1,"commentor":931,"gmtCreate":null,"gmtModified":null,"like_count":0,"content":"我有时候即使过了脑子 因为情绪还是想说难听话 即使知道如果要顾大局有些话不该说 但真的忍不住 回头想想也挺后悔的 一时痛快导致后面失去更多","anonymity":1,"any_name":"水箭龟","commentCount":null,"user":{"id":931,"name":"fengli","avatar_url":"http://test01-20200725.oss-cn-shenzhen.aliyuncs.com/image/1666425162084.jpg?Expires=1981785154&OSSAccessKeyId=LTAI4G5RL7pjavqASCwc42kR&Signature=sX%2BG7c2ycJYoXZat%2FkI3BiYTZjI%3D"},"isCommentLike":-5,"dislike_count":0}],"any_name":"微积分","relation":-2,"liked":-4,"anonymity":1,"dislike_count":0}